{
  "$schema": "https://developer.microsoft.com/json-schemas/fabric/item/report/definition/visualContainerMobileState/2.1.0/schema.json",
  "position": {
    "x": 126,
    "y": 0,
    "z": 4000,
    "height": 32,
    "width": 198,
    "tabOrder": 4000
  },
  "objects": {
    "shape": [],
    "rotation": [],
    "text": [
      {
        "properties": {
          "fontFamily": {
            "expr": {
              "Literal": {
                "Value": "'''Segoe UI Semibold'', wf_segoe-ui_semibold, helvetica, arial, sans-serif'"
              }
            }
          },
          "fontSize": {
            "expr": {
              "Literal": {
                "Value": "8D"
              }
            }
          },
          "fontColor": {
            "solid": {
              "color": {
                "expr": {
                  "Literal": {
                    "Value": "'#144E75'"
                  }
                }
              }
            }
          }
        },
        "selector": {
          "id": "default"
        }
      }
    ],
    "outline": [],
    "fill": []
  }
}